fast_tor_requests/__init__.py
fast_tor_requests/client.py
fast_tor_requests/tor_binary.py
fast_tor_requests/tor_manager.py
fast_tor_requests-0.3.0.dist-info/METADATA
fast_tor_requests-0.3.0.dist-info/WHEEL
fast_tor_requests-0.3.0.dist-info/top_level.txt
fast_tor_requests-0.3.0.dist-info/RECORD
