Metadata-Version: 2.4
Name: fast-tor-requests
Version: 0.3.0
Summary: Fast drop-in replacement for requests.Session using Tor
Author: Your Name
Classifier: Programming Language :: Python :: 3
Classifier: License :: OSI Approved :: MIT License
Classifier: Operating System :: OS Independent
Requires-Python: >=3.8
Requires-Dist: requests
Requires-Dist: pysocks
